{
  "backend": "houdini",
  "composition_sha256": "9d977d9c92211f0ef1033f80e3da240ec2e7811e75323a6c07814ed6dbdd8ad7",
  "face_modules": [
    "core",
    "core",
    "core",
    "core",
    "left-branch",
    "left-branch",
    "left-branch",
    "left-branch",
    "left-branch",
    "left-branch",
    "left-branch",
    "left-branch",
    "left-branch",
    "left-branch",
    "left-branch",
    "left-branch",
    "left-branch",
    "left-branch",
    "left-branch",
    "left-branch",
    "right-branch",
    "right-branch",
    "right-branch",
    "right-branch",
    "right-branch",
    "right-branch",
    "right-branch",
    "right-branch",
    "right-branch",
    "right-branch",
    "right-branch",
    "right-branch",
    "right-branch",
    "right-branch",
    "right-branch",
    "right-branch"
  ],
  "faces": [
    [
      0,
      4,
      5,
      1
    ],
    [
      0,
      3,
      7,
      4
    ],
    [
      3,
      2,
      6,
      7
    ],
    [
      1,
      5,
      6,
      2
    ],
    [
      0,
      1,
      9,
      8
    ],
    [
      1,
      2,
      10,
      9
    ],
    [
      2,
      3,
      11,
      10
    ],
    [
      3,
      0,
      8,
      11
    ],
    [
      8,
      9,
      13,
      12
    ],
    [
      9,
      10,
      14,
      13
    ],
    [
      10,
      11,
      15,
      14
    ],
    [
      11,
      8,
      12,
      15
    ],
    [
      12,
      13,
      17,
      16
    ],
    [
      13,
      14,
      18,
      17
    ],
    [
      14,
      15,
      19,
      18
    ],
    [
      15,
      12,
      16,
      19
    ],
    [
      20,
      17,
      16
    ],
    [
      20,
      18,
      17
    ],
    [
      20,
      19,
      18
    ],
    [
      20,
      16,
      19
    ],
    [
      4,
      5,
      22,
      21
    ],
    [
      5,
      6,
      23,
      22
    ],
    [
      6,
      7,
      24,
      23
    ],
    [
      7,
      4,
      21,
      24
    ],
    [
      21,
      22,
      26,
      25
    ],
    [
      22,
      23,
      27,
      26
    ],
    [
      23,
      24,
      28,
      27
    ],
    [
      24,
      21,
      25,
      28
    ],
    [
      25,
      26,
      30,
      29
    ],
    [
      26,
      27,
      31,
      30
    ],
    [
      27,
      28,
      32,
      31
    ],
    [
      28,
      25,
      29,
      32
    ],
    [
      33,
      30,
      29
    ],
    [
      33,
      31,
      30
    ],
    [
      33,
      32,
      31
    ],
    [
      33,
      29,
      32
    ]
  ],
  "regions": [
    {
      "branch": 0.0,
      "core": 1.0
    },
    {
      "branch": 0.0,
      "core": 1.0
    },
    {
      "branch": 0.0,
      "core": 1.0
    },
    {
      "branch": 0.0,
      "core": 1.0
    },
    {
      "branch": 0.0,
      "core": 1.0
    },
    {
      "branch": 0.0,
      "core": 1.0
    },
    {
      "branch": 0.0,
      "core": 1.0
    },
    {
      "branch": 0.0,
      "core": 1.0
    },
    {
      "branch": 1.0,
      "core": 0.0
    },
    {
      "branch": 1.0,
      "core": 0.0
    },
    {
      "branch": 1.0,
      "core": 0.0
    },
    {
      "branch": 1.0,
      "core": 0.0
    },
    {
      "branch": 1.0,
      "core": 0.0
    },
    {
      "branch": 1.0,
      "core": 0.0
    },
    {
      "branch": 1.0,
      "core": 0.0
    },
    {
      "branch": 1.0,
      "core": 0.0
    },
    {
      "branch": 1.0,
      "core": 0.0
    },
    {
      "branch": 1.0,
      "core": 0.0
    },
    {
      "branch": 1.0,
      "core": 0.0
    },
    {
      "branch": 1.0,
      "core": 0.0
    },
    {
      "branch": 1.0,
      "core": 0.0
    },
    {
      "branch": 1.0,
      "core": 0.0
    },
    {
      "branch": 1.0,
      "core": 0.0
    },
    {
      "branch": 1.0,
      "core": 0.0
    },
    {
      "branch": 1.0,
      "core": 0.0
    },
    {
      "branch": 1.0,
      "core": 0.0
    },
    {
      "branch": 1.0,
      "core": 0.0
    },
    {
      "branch": 1.0,
      "core": 0.0
    },
    {
      "branch": 1.0,
      "core": 0.0
    },
    {
      "branch": 1.0,
      "core": 0.0
    },
    {
      "branch": 1.0,
      "core": 0.0
    },
    {
      "branch": 1.0,
      "core": 0.0
    },
    {
      "branch": 1.0,
      "core": 0.0
    },
    {
      "branch": 1.0,
      "core": 0.0
    }
  ],
  "schema": "socket-adapter-readback/0",
  "socket": {
    "branch_rings": {
      "left": [
        [
          8,
          9,
          10,
          11
        ],
        [
          12,
          13,
          14,
          15
        ],
        [
          16,
          17,
          18,
          19
        ]
      ],
      "right": [
        [
          21,
          22,
          23,
          24
        ],
        [
          25,
          26,
          27,
          28
        ],
        [
          29,
          30,
          31,
          32
        ]
      ]
    },
    "caps": {
      "left": 20,
      "right": 33
    },
    "frames": {
      "left": {
        "origin": [
          -0.21,
          0.0,
          0.0
        ],
        "tangent": [
          -1.0,
          0.0,
          0.0
        ],
        "u": [
          0.0,
          1.0,
          0.0
        ],
        "v": [
          0.0,
          0.0,
          1.0
        ]
      },
      "right": {
        "origin": [
          0.21,
          0.0,
          0.0
        ],
        "tangent": [
          1.0,
          0.0,
          0.0
        ],
        "u": [
          0.0,
          1.0,
          0.0
        ],
        "v": [
          0.0,
          0.0,
          1.0
        ]
      }
    },
    "interfaces": {
      "left": [
        0,
        1,
        2,
        3
      ],
      "right": [
        4,
        5,
        6,
        7
      ]
    },
    "mirror_pairs": [
      [
        0,
        4
      ],
      [
        1,
        5
      ],
      [
        2,
        6
      ],
      [
        3,
        7
      ],
      [
        8,
        21
      ],
      [
        9,
        22
      ],
      [
        10,
        23
      ],
      [
        11,
        24
      ],
      [
        12,
        25
      ],
      [
        13,
        26
      ],
      [
        14,
        27
      ],
      [
        15,
        28
      ],
      [
        16,
        29
      ],
      [
        17,
        30
      ],
      [
        18,
        31
      ],
      [
        19,
        32
      ],
      [
        20,
        33
      ]
    ]
  },
  "version": "22.0.368",
  "vertex_modules": [
    "core-branch-socket",
    "core-branch-socket",
    "core-branch-socket",
    "core-branch-socket",
    "core-branch-socket",
    "core-branch-socket",
    "core-branch-socket",
    "core-branch-socket",
    "left-branch",
    "left-branch",
    "left-branch",
    "left-branch",
    "left-branch",
    "left-branch",
    "left-branch",
    "left-branch",
    "left-branch",
    "left-branch",
    "left-branch",
    "left-branch",
    "left-branch",
    "right-branch",
    "right-branch",
    "right-branch",
    "right-branch",
    "right-branch",
    "right-branch",
    "right-branch",
    "right-branch",
    "right-branch",
    "right-branch",
    "right-branch",
    "right-branch",
    "right-branch"
  ],
  "vertices": [
    [
      -0.20999999344348907,
      -0.10999999940395355,
      -0.2800000011920929
    ],
    [
      -0.20999999344348907,
      0.10999999940395355,
      -0.2800000011920929
    ],
    [
      -0.20999999344348907,
      0.10999999940395355,
      0.2800000011920929
    ],
    [
      -0.20999999344348907,
      -0.10999999940395355,
      0.2800000011920929
    ],
    [
      0.20999999344348907,
      -0.10999999940395355,
      -0.2800000011920929
    ],
    [
      0.20999999344348907,
      0.10999999940395355,
      -0.2800000011920929
    ],
    [
      0.20999999344348907,
      0.10999999940395355,
      0.2800000011920929
    ],
    [
      0.20999999344348907,
      -0.10999999940395355,
      0.2800000011920929
    ],
    [
      -0.33666667342185974,
      -0.10001851618289948,
      -0.2545925974845886
    ],
    [
      -0.33666667342185974,
      0.10001851618289948,
      -0.2545925974845886
    ],
    [
      -0.33666667342185974,
      0.10001851618289948,
      0.2545925974845886
    ],
    [
      -0.33666667342185974,
      -0.10001851618289948,
      0.2545925974845886
    ],
    [
      -0.4633333384990692,
      -0.08148147910833359,
      -0.2074074000120163
    ],
    [
      -0.4633333384990692,
      0.08148147910833359,
      -0.2074074000120163
    ],
    [
      -0.4633333384990692,
      0.08148147910833359,
      0.2074074000120163
    ],
    [
      -0.4633333384990692,
      -0.08148147910833359,
      0.2074074000120163
    ],
    [
      -0.5899999737739563,
      -0.07150000333786011,
      -0.18199999630451202
    ],
    [
      -0.5899999737739563,
      0.07150000333786011,
      -0.18199999630451202
    ],
    [
      -0.5899999737739563,
      0.07150000333786011,
      0.18199999630451202
    ],
    [
      -0.5899999737739563,
      -0.07150000333786011,
      0.18199999630451202
    ],
    [
      -0.5899999737739563,
      0.0,
      0.0
    ],
    [
      0.33666667342185974,
      -0.10001851618289948,
      -0.2545925974845886
    ],
    [
      0.33666667342185974,
      0.10001851618289948,
      -0.2545925974845886
    ],
    [
      0.33666667342185974,
      0.10001851618289948,
      0.2545925974845886
    ],
    [
      0.33666667342185974,
      -0.10001851618289948,
      0.2545925974845886
    ],
    [
      0.4633333384990692,
      -0.08148147910833359,
      -0.2074074000120163
    ],
    [
      0.4633333384990692,
      0.08148147910833359,
      -0.2074074000120163
    ],
    [
      0.4633333384990692,
      0.08148147910833359,
      0.2074074000120163
    ],
    [
      0.4633333384990692,
      -0.08148147910833359,
      0.2074074000120163
    ],
    [
      0.5899999737739563,
      -0.07150000333786011,
      -0.18199999630451202
    ],
    [
      0.5899999737739563,
      0.07150000333786011,
      -0.18199999630451202
    ],
    [
      0.5899999737739563,
      0.07150000333786011,
      0.18199999630451202
    ],
    [
      0.5899999737739563,
      -0.07150000333786011,
      0.18199999630451202
    ],
    [
      0.5899999737739563,
      0.0,
      0.0
    ]
  ]
}
